LICENSE.txt
MANIFEST.in
README.md
setup.py
PcapGraph.egg-info/PKG-INFO
PcapGraph.egg-info/SOURCES.txt
PcapGraph.egg-info/dependency_links.txt
PcapGraph.egg-info/entry_points.txt
PcapGraph.egg-info/top_level.txt
pcapgraph/__init__.py
pcapgraph/draw_graph.py
pcapgraph/generate_example_pcaps.py
pcapgraph/get_filenames.py
pcapgraph/manipulate_frames.py
pcapgraph/pcap_math.py
pcapgraph/pcapgraph.py
pcapgraph/save_file.py