Metadata-Version: 2.1
Name: PcapGraph
Version: 1.3.0
Summary: Create a graph out of packet captures.
Home-page: https://www.github.com/pocc/pcapgraph/
Author: Ross Jacobs
Author-email: whim42+pcapgraph@gmail.com
License: Apache 2.0
Download-URL: https://github.com/pocc/pcapgraph/releases
Platform: UNKNOWN
Classifier: Development Status :: 4 - Beta
Classifier: License :: OSI Approved :: Apache Software License
Classifier: Intended Audience :: Developers
Classifier: Intended Audience :: Information Technology
Classifier: Intended Audience :: System Administrators
Classifier: Intended Audience :: Telecommunications Industry
Classifier: Operating System :: MacOS
Classifier: Operating System :: Microsoft :: Windows
Classifier: Operating System :: POSIX :: Linux
Classifier: Programming Language :: Python :: 3
Classifier: Programming Language :: Python :: 3.5
Classifier: Programming Language :: Python :: 3.6
Classifier: Programming Language :: Python :: 3.7
Classifier: Topic :: System :: Monitoring
Classifier: Topic :: System :: Networking
Classifier: Topic :: System :: Networking :: Monitoring
Classifier: Topic :: Utilities
Provides: pcapgraph
Requires-Python: >=3.5
